README.rst
setup.py
git_todo/__init__.py
git_todo/cli.py
git_todo/parser.py
git_todo/todo.py
git_todo.egg-info/PKG-INFO
git_todo.egg-info/SOURCES.txt
git_todo.egg-info/dependency_links.txt
git_todo.egg-info/entry_points.txt
git_todo.egg-info/requires.txt
git_todo.egg-info/top_level.txt