Metadata-Version: 1.1
Name: git-todo
Version: 0.1
Summary: Tracks issues and TODOs in a standalone branch in your repository.
Home-page: https://github.com/mbr/git-todo
Author: Marc Brinkmann
Author-email: git@marcbrinkmann.de
License: MIT
Platform: UNKNOWN
Classifier: Programming Language :: Python :: 2
Classifier: Programming Language :: Python :: 3
